[
  {
    "name": "point_tracker",
    "options": {
      "num_points": 33,
      "point_color": "#15718a",
      "text_color": "#5916f7",
      "spline_color": "#56f1e5",
      "spline_type": "polyline",
      "show_bbox": false
    }
  },
  {
    "name": "color_adjust",
    "options": {
      "hue_shift": 50,
      "saturation_scale": 1.68,
      "luminosity_scale": 1.1,
      "contrast": 0.13,
      "brightness": 99
    }
  },
  {
    "name": "double_exposure",
    "options": {
      "delay_frames": 4,
      "opacity": 0.76
    }
  },
  {
    "name": "tracking",
    "options": {
      "draw_tesselation": false,
      "line_thickness": 3,
      "line_color": "#1ef90e",
      "overlay_image_path": "",
      "overlay_size": 33
    }
  },
  {
    "name": "solarize",
    "options": {
      "threshold": 10
    }
  },
  {
    "name": "datamosh",
    "options": {
      "gop_size": 1000,
      "qscale": 31
    }
  }
]